{
  "apps": [
    {
      "name": "nodejs_api",
      "script": "dist/src/server.js",
      "instances": 1,
      "autorestart": true,
      "watch": false,
      "time": true,
      "env": {
        "MAIN_DOMAIN": ".gomanager.app",
        "NODE_ENV": "production",
        "PORT": 4000,
        "ENV": "production",
        "JWT_SECRET": "secret",
        "WHITELIST_DOMAINS": "http://localhost:3000,http://localhost:8080,https://71d7-105-33-232-37.ngrok-free.app,https://new.zadulquran.com,https://zadul.gomanager.app",
        "POSTGRES_USERNAME": "omar",
        "POSTGRES_PASSWORD": "password",
        "POSTGRES_DATABASE": "zadul",
        "POSTGRES_HOST": "179.61.219.66",
        "DB_HOST": "179.61.219.66",
        "ZOOM_CLIENT_ID": "JvukpC3SKSuwCbwE1Lh_A",
        "ZOOM_SECRET_KEY": "JF8lgpsybwDadvS0snPQvDfwCaCSz9OV"
      },
      "listen_address": "::",
      "port": 4000
    }
  ]
}
